promptly_ai/__init__.py
promptly_ai/manager.py
promptly_ai-0.2.0.dist-info/METADATA
promptly_ai-0.2.0.dist-info/WHEEL
promptly_ai-0.2.0.dist-info/licenses/LICENSE
promptly_ai-0.2.0.dist-info/RECORD
